{".class": "MypyFile", "_fullname": "torch.ao.sparsity.sparsifier", "is_partial_stub_package": false, "is_stub": false, "names": {".class": "SymbolTable", "__doc__": {".class": "SymbolTableNode", "kind": "Gdef", "node": {".class": "Var", "flags": ["is_ready"], "fullname": "torch.ao.sparsity.sparsifier.__doc__", "name": "__doc__", "type": "builtins.str"}}, "__file__": {".class": "SymbolTableNode", "kind": "Gdef", "node": {".class": "Var", "flags": ["is_ready"], "fullname": "torch.ao.sparsity.sparsifier.__file__", "name": "__file__", "type": "builtins.str"}}, "__name__": {".class": "SymbolTableNode", "kind": "Gdef", "node": {".class": "Var", "flags": ["is_ready"], "fullname": "torch.ao.sparsity.sparsifier.__name__", "name": "__name__", "type": "builtins.str"}}, "__package__": {".class": "SymbolTableNode", "kind": "Gdef", "node": {".class": "Var", "flags": ["is_ready"], "fullname": "torch.ao.sparsity.sparsifier.__package__", "name": "__package__", "type": "builtins.str"}}}, "path": "/home/patrick/anaconda3/lib/python3.9/site-packages/torch/ao/sparsity/sparsifier/__init__.py"}